README.md
setup.py
mwbyd/__init__.py
mwbyd/my_module.py
mwbyd/test.py
mwbyd.egg-info/PKG-INFO
mwbyd.egg-info/SOURCES.txt
mwbyd.egg-info/dependency_links.txt
mwbyd.egg-info/top_level.txt