Metadata-Version: 2.1
Name: mwbyd
Version: 1.0.13
Summary: 哈哈哈
Home-page: http://github.com/kts168/mwbyd
Author: kts168
Author-email: kts168@163.com
License: UNKNOWN
Platform: UNKNOWN
Classifier: Programming Language :: Python :: 3
Classifier: License :: OSI Approved :: MIT License
Classifier: Operating System :: OS Independent
